.env.example
MANIFEST.in
README.md
setup.py
lebara_api/__init__.py
lebara_api/command_line.py
lebara_api.egg-info/PKG-INFO
lebara_api.egg-info/SOURCES.txt
lebara_api.egg-info/dependency_links.txt
lebara_api.egg-info/entry_points.txt
lebara_api.egg-info/not-zip-safe
lebara_api.egg-info/requires.txt
lebara_api.egg-info/top_level.txt