Metadata-Version: 1.0
Name: lebara-api
Version: 0.3.0
Summary: lebara api
Home-page: https://github.com/tlan16/lebara-api
Author: Frank Lan
Author-email: franklan118@gmail.com
License: GPL-3.0
Platform: UNKNOWN
